MANIFEST.in
README.txt
plonetheme.bluegray-configure.zcml
setup.py
docs/AUTHORS.txt
docs/HISTORY.txt
docs/INSTALL.txt
docs/LICENSE.GPL
docs/LICENSE.txt
plonetheme/__init__.py
plonetheme.bluegray.egg-info/PKG-INFO
plonetheme.bluegray.egg-info/SOURCES.txt
plonetheme.bluegray.egg-info/dependency_links.txt
plonetheme.bluegray.egg-info/entry_points.txt
plonetheme.bluegray.egg-info/namespace_packages.txt
plonetheme.bluegray.egg-info/not-zip-safe
plonetheme.bluegray.egg-info/requires.txt
plonetheme.bluegray.egg-info/top_level.txt
plonetheme/bluegray/__init__.py
plonetheme/bluegray/configure.zcml
plonetheme/bluegray/profiles.zcml
plonetheme/bluegray/setuphandlers.py
plonetheme/bluegray/skins.zcml
plonetheme/bluegray/tests.py
plonetheme/bluegray/version.txt
plonetheme/bluegray/browser/__init__.py
plonetheme/bluegray/browser/configure.zcml
plonetheme/bluegray/browser/interfaces.py
plonetheme/bluegray/browser/viewlet.pt
plonetheme/bluegray/browser/viewlets.py
plonetheme/bluegray/browser/images/README.txt
plonetheme/bluegray/browser/images/cruz-down.gif
plonetheme/bluegray/browser/images/cruz.gif
plonetheme/bluegray/browser/images/leftcontent.jpg
plonetheme/bluegray/browser/images/leftcontentbottom.jpg
plonetheme/bluegray/browser/images/rightcontent-botton-white.gif
plonetheme/bluegray/browser/images/rightcontent-white.gif
plonetheme/bluegray/browser/images/rightcontent.jpg
plonetheme/bluegray/browser/images/rightcontentbottom.jpg
plonetheme/bluegray/browser/scripts/README.txt
plonetheme/bluegray/browser/stylesheets/README.txt
plonetheme/bluegray/browser/templates/sections.pt
plonetheme/bluegray/browser/templates/site_actions.pt
plonetheme/bluegray/profiles/default/cssregistry.xml
plonetheme/bluegray/profiles/default/import_steps.xml
plonetheme/bluegray/profiles/default/jsregistry.xml
plonetheme/bluegray/profiles/default/login.xml
plonetheme/bluegray/profiles/default/metadata.xml
plonetheme/bluegray/profiles/default/plonetheme.bluegray_various.txt
plonetheme/bluegray/profiles/default/skins.xml
plonetheme/bluegray/profiles/default/viewlets.xml
plonetheme/bluegray/skins/plonetheme_bluegray_custom_images/CONTENT.txt
plonetheme/bluegray/skins/plonetheme_bluegray_custom_images/bullet.gif
plonetheme/bluegray/skins/plonetheme_bluegray_custom_images/bulletBig.gif
