Metadata-Version: 1.0
Name: plonetheme.bluegray
Version: 1.0.0b2
Summary: An installable theme for Plone
Home-page: http://plone.org/products/plonetheme-bluegray/
Author: Noelia Chaves, Marcelo Huens
Author-email: info@menttes.com
License: GPL
Keywords: web zope plone theme
Platform: UNKNOWN
Classifier: Framework :: Plone
Classifier: Programming Language :: Python
Classifier: Topic :: Software Development :: Libraries :: Python Modules
